acp_evals/README.md
acp_evals/__init__.py
acp_evals/__main__.py
acp_evals/api.py
acp_evals/cli/__init__.py
acp_evals/cli/check.py
acp_evals/cli/display.py
acp_evals/cli/main.py
acp_evals/cli/templates.py
acp_evals/cli/commands/__init__.py
acp_evals/cli/commands/comprehensive.py
acp_evals/cli/commands/discover.py
acp_evals/cli/commands/quickstart.py
acp_evals/cli/commands/run.py
acp_evals/cli/commands/test.py
acp_evals/core/__init__.py
acp_evals/core/acp_diagnostics.py
acp_evals/core/base.py
acp_evals/core/config.py
acp_evals/core/exceptions.py
acp_evals/core/validation.py
acp_evals/evaluators/__init__.py
acp_evals/evaluators/accuracy.py
acp_evals/evaluators/common.py
acp_evals/evaluators/llm_judge.py
acp_evals/evaluators/performance.py
acp_evals/evaluators/reliability.py
acp_evals/providers/__init__.py
acp_evals/providers/anthropic_provider.py
acp_evals/providers/base.py
acp_evals/providers/factory.py
acp_evals/providers/ollama_provider.py
acp_evals/providers/openai_provider.py
acp_evals/server/__init__.py
acp_evals/server/acp_server.py
acp_evals/utils/__init__.py
acp_evals/utils/logging.py
acp_evals-1.0.0.dist-info/METADATA
acp_evals-1.0.0.dist-info/WHEEL
acp_evals-1.0.0.dist-info/entry_points.txt
acp_evals-1.0.0.dist-info/licenses/LICENSE
acp_evals-1.0.0.dist-info/RECORD
