Metadata-Version: 2.4
Name: acp-evals
Version: 1.0.0
Summary: Production-grade evaluation framework for Agent Communication Protocol (ACP) agents
Project-URL: Homepage, https://github.com/jbarnes850/acp-evals
Project-URL: Documentation, https://github.com/jbarnes850/acp-evals/tree/main/docs
Project-URL: Repository, https://github.com/jbarnes850/acp-evals
Project-URL: Issues, https://github.com/jbarnes850/acp-evals/issues
Author-email: Jarrod Barnes <jbarnes850@gmail.com>
License: Apache-2.0
License-File: LICENSE
Keywords: acp,agents,ai,evaluation,llm,performance,quality,reliability,testing
Classifier: Development Status :: 5 - Production/Stable
Classifier: Intended Audience :: Developers
Classifier: License :: OSI Approved :: Apache Software License
Classifier: Programming Language :: Python :: 3
Classifier: Programming Language :: Python :: 3.11
Classifier: Programming Language :: Python :: 3.12
Classifier: Topic :: Scientific/Engineering :: Artificial Intelligence
Classifier: Topic :: Software Development :: Testing
Classifier: Topic :: System :: Benchmark
Requires-Python: >=3.11
Requires-Dist: acp-sdk>=0.1.0
Requires-Dist: asyncio>=3.4.3
Requires-Dist: click>=8.0.0
Requires-Dist: httpx>=0.24.0
Requires-Dist: numpy>=1.24.0
Requires-Dist: opentelemetry-api>=1.20.0
Requires-Dist: opentelemetry-exporter-otlp-proto-http>=1.20.0
Requires-Dist: opentelemetry-sdk>=1.20.0
Requires-Dist: pandas>=2.0.0
Requires-Dist: pydantic>=2.0.0
Requires-Dist: python-dotenv>=1.0.0
Requires-Dist: rich>=13.0.0
Requires-Dist: tiktoken>=0.5.0
Provides-Extra: all-providers
Requires-Dist: anthropic>=0.21.0; extra == 'all-providers'
Requires-Dist: openai>=1.0.0; extra == 'all-providers'
Provides-Extra: anthropic
Requires-Dist: anthropic>=0.21.0; extra == 'anthropic'
Provides-Extra: dev
Requires-Dist: pyright>=1.1.0; extra == 'dev'
Requires-Dist: pytest-asyncio>=0.21.0; extra == 'dev'
Requires-Dist: pytest-cov>=4.1.0; extra == 'dev'
Requires-Dist: pytest>=7.4.0; extra == 'dev'
Requires-Dist: ruff>=0.1.0; extra == 'dev'
Provides-Extra: openai
Requires-Dist: openai>=1.0.0; extra == 'openai'
